jclip/__init__.py
jclip/__main__.py
jclip/cli.py
jclip/copier.py
jclip-0.1.0.dist-info/licenses/LICENSE
jclip-0.1.0.dist-info/METADATA
jclip-0.1.0.dist-info/WHEEL
jclip-0.1.0.dist-info/entry_points.txt
jclip-0.1.0.dist-info/top_level.txt
jclip-0.1.0.dist-info/RECORD
