Metadata-Version: 2.4
Name: jclip
Version: 0.1.0
Summary: clipboard copier for pentesting
Author-email: Javen Beck <javensbeck@gmail.com>
License-File: LICENSE
Requires-Dist: typer
Requires-Dist: typing_extensions
Requires-Dist: pyperclip
Dynamic: license-file
